s2reader3
