Metadata-Version: 1.1
Name: s2reader3
Version: 0.6.3
Summary: simple Python 3 metadata reader for Sentinel-2 SAFE files (Level-1C and Level-2A), derived from old unsupported Python 2 s2reader3 of https://github.com/ungarj/s2reader.git
Home-page: https://github.com/robert-werner/s2reader3.git
Author: Leonid Kolesnichenko
Author-email: xperience439@gmail.com
License: MIT
Platform: UNKNOWN
Classifier: Development Status :: 3 - Alpha
Classifier: Intended Audience :: Developers
Classifier: Topic :: Scientific/Engineering :: GIS
Classifier: License :: OSI Approved :: MIT License
Classifier: Programming Language :: Python :: 3.7
